opencv_mcp_server/__init__.py
opencv_mcp_server/computer_vision.py
opencv_mcp_server/image_basics.py
opencv_mcp_server/image_processing.py
opencv_mcp_server/main.py
opencv_mcp_server/utils.py
opencv_mcp_server/video_processing.py
opencv_mcp_server-0.1.2.dist-info/METADATA
opencv_mcp_server-0.1.2.dist-info/WHEEL
opencv_mcp_server-0.1.2.dist-info/entry_points.txt
opencv_mcp_server-0.1.2.dist-info/licenses/LICENSE
opencv_mcp_server-0.1.2.dist-info/RECORD
